beast2_xml-1.5.1.data/scripts/beast2-xml-version.py
beast2_xml-1.5.1.data/scripts/beast2-xml.py
beast2_xml-1.5.1.dist-info/licenses/LICENSE
beast2xml/__init__.py
beast2xml/beast2.py
beast2xml/date_utilities.py
beast2xml/templates/random-local.xml
beast2xml/templates/relaxed-exponential.xml
beast2xml/templates/relaxed-lognormal.xml
beast2xml/templates/strict.xml
beast2_xml-1.5.1.dist-info/METADATA
beast2_xml-1.5.1.dist-info/WHEEL
beast2_xml-1.5.1.dist-info/top_level.txt
beast2_xml-1.5.1.dist-info/RECORD
