Metadata-Version: 2.4
Name: beast2-xml
Version: 1.5.1
Summary: Command line script and Python class for generating BEAST2 XML config files.
Home-page: https://github.com/acorg/beast2-xml
Download-URL: https://github.com/acorg/beast2-xml
Author: Terry Jones
Author-email: tcj25@cam.ac.uk
License: MIT
Keywords: BEAST2,XML
Classifier: Programming Language :: Python :: 3.10
Classifier: Development Status :: 4 - Beta
Classifier: Intended Audience :: Developers
Classifier: License :: OSI Approved :: MIT License
Classifier: Operating System :: OS Independent
Classifier: Topic :: Software Development :: Libraries :: Python Modules
License-File: LICENSE
Requires-Dist: dark-matter>=1.1.28
Requires-Dist: pandas>=2.2.2
Requires-Dist: ete3>=3.1.3
Requires-Dist: six>=1.16.0
Requires-Dist: numpy>=1.10.0
Dynamic: author
Dynamic: author-email
Dynamic: classifier
Dynamic: description
Dynamic: download-url
Dynamic: home-page
Dynamic: keywords
Dynamic: license
Dynamic: license-file
Dynamic: requires-dist
Dynamic: summary
